yourmove/__init__.py
yourmove/models.py
yourmove/settings.py
yourmove-0.0.0.1.dist-info/LICENSE
yourmove-0.0.0.1.dist-info/METADATA
yourmove-0.0.0.1.dist-info/WHEEL
yourmove-0.0.0.1.dist-info/top_level.txt
yourmove-0.0.0.1.dist-info/RECORD
