Metadata-Version: 2.1
Name: yourmove
Version: 0.0.0.1
Summary: YourMove
Home-page: https://cwphs.ucsd.edu
Author: jup014
Author-email: jup014@ucsd.edu
License: MIT
Platform: UNKNOWN
Requires-Python: >=3
License-File: LICENSE
Requires-Dist: pytz
